hccpy/_AGESEXV2.py
hccpy/_AGESEXV6.py
hccpy/_E2118P1M.py
hccpy/_E2118P1P.py
hccpy/_I0V05ED2.py
hccpy/_V0519F3M.py
hccpy/_V0519F3P.py
hccpy/_V2218O1M.py
hccpy/_V2218O1P.py
hccpy/_V22I0ED2.py
hccpy/_V2318P1M.py
hccpy/_V2419P1M.py
hccpy/_V2823T2M.py
hccpy/_V28I0ED1.py
hccpy/__init__.py
hccpy/hcc.py
hccpy/hhshcc.py
hccpy/raeligible.py
hccpy/utils.py
hccpy/utils_hhs.py
hccpy/__pycache__/_AGESEXV2.cpython-37.pyc
hccpy/__pycache__/_AGESEXV6.cpython-37.pyc
hccpy/__pycache__/_E2118P1M.cpython-37.pyc
hccpy/__pycache__/_E2118P1P.cpython-37.pyc
hccpy/__pycache__/_I0V05ED2.cpython-37.pyc
hccpy/__pycache__/_V0519F3M.cpython-37.pyc
hccpy/__pycache__/_V0519F3P.cpython-37.pyc
hccpy/__pycache__/_V2218O1M.cpython-37.pyc
hccpy/__pycache__/_V2218O1P.cpython-37.pyc
hccpy/__pycache__/_V22I0ED2.cpython-37.pyc
hccpy/__pycache__/_V2318P1M.cpython-37.pyc
hccpy/__pycache__/_V2419P1M.cpython-37.pyc
hccpy/__pycache__/_V2823T2M.cpython-37.pyc
hccpy/__pycache__/_V28I0ED1.cpython-37.pyc
hccpy/__pycache__/__init__.cpython-37.pyc
hccpy/__pycache__/hcc.cpython-37.pyc
hccpy/__pycache__/hhshcc.cpython-37.pyc
hccpy/__pycache__/utils.cpython-37.pyc
hccpy/__pycache__/utils_hhs.cpython-37.pyc
hccpy/data/AGESEXV2.TXT
hccpy/data/AGESEXV6.TXT
hccpy/data/CY22F07A_FY 2022 ICD10.TXT
hccpy/data/CY22F07A_HCPCS8_1_22_04.TXT
hccpy/data/CY22F07A_NDC8_1_22_04.TXT
hccpy/data/E2118P1M.txt
hccpy/data/ESRDhcccoefn.csv
hccpy/data/F2118H1R.txt
hccpy/data/F2217O1P.TXT
hccpy/data/F2218O1P.TXT
hccpy/data/F2219O1P.TXT
hccpy/data/F2220O1P.TXT
hccpy/data/F2221O1P.TXT
hccpy/data/F2221O2P.TXT
hccpy/data/F2222O1P.TXT
hccpy/data/F22_AllYearsCombined.TXT
hccpy/data/F2318P1Q.TXT
hccpy/data/F2319P1Q.TXT
hccpy/data/F23_AllYearsCombined.TXT
hccpy/data/F2419P1M.TXT
hccpy/data/F2420P1M.TXT
hccpy/data/F2421P1M.TXT
hccpy/data/F2421P2M.TXT
hccpy/data/F2422P1M.TXT
hccpy/data/F24_AllYearsCombined.TXT
hccpy/data/F2823T2N_FY20FY21.TXT
hccpy/data/F2823T2N_FY22FY23.TXT
hccpy/data/H0519F3.FY 2018 ICD10.TXT
hccpy/data/H0519F3.FY 2019 ICD10.TXT
hccpy-0.1.9.dist-info/LICENSE.txt
hccpy-0.1.9.dist-info/METADATA
hccpy-0.1.9.dist-info/WHEEL
hccpy-0.1.9.dist-info/top_level.txt
hccpy-0.1.9.dist-info/RECORD
