Metadata-Version: 2.1
Name: hccpy
Version: 0.1.9
Summary: hccpy is a Python implementation of HCC
Home-page: https://github.com/yubin-park/hccpy
Author: Yubin Park
Author-email: yubin.park@gmail.com
License: Apache 2.0
Classifier: Programming Language :: Python :: 3
Classifier: License :: OSI Approved :: Apache Software License
Classifier: Operating System :: OS Independent
License-File: LICENSE.txt
Requires-Dist: numpy
